nordicintel/__init__.py
nordicintel-0.0.0.dist-info/METADATA
nordicintel-0.0.0.dist-info/WHEEL
nordicintel-0.0.0.dist-info/top_level.txt
nordicintel-0.0.0.dist-info/RECORD
